.meta_version
CONTRIBUTE.md
LICENSE
MANIFEST.in
README.md
requirements.txt
setup.py
test.py
btm/__init__.py
btm/collections.py
btm/core.py
btm/info.py
btmod.egg-info/PKG-INFO
btmod.egg-info/SOURCES.txt
btmod.egg-info/dependency_links.txt
btmod.egg-info/entry_points.txt
btmod.egg-info/not-zip-safe
btmod.egg-info/top_level.txt