Metadata-Version: 2.1
Name: btmod
Version: 1.0.1
Summary: Modify Python Built-in Types
Home-page: https://github.com/nacho00112/btm
Author: Nacho00112
Author-email: thurealrubiogame@gmail.com
License: mit
Download-URL: https://github.com/nacho00112/btm/archive/v1.0.1.tar.gz
Platform: any
Classifier: Programming Language :: Python :: 3.7
Classifier: Programming Language :: Python :: Implementation :: CPython
Requires-Python: >=3.7
